dotsetup/__init__.py
dotsetup/exception.py
dotsetup/parse.py
dotsetup/version.py
dotsetup-0.0.1.dist-info/LICENSE
dotsetup-0.0.1.dist-info/METADATA
dotsetup-0.0.1.dist-info/WHEEL
dotsetup-0.0.1.dist-info/top_level.txt
dotsetup-0.0.1.dist-info/RECORD
