Metadata-Version: 2.1
Name: dotsetup
Version: 0.0.1
Summary: A simple setup tool for Python projects to manage environment variables and configurations ands settings.
Home-page: https://github.com/muhammad-fiaz/dotsetup
Author: Muhammad Fiaz
Author-email: fiazatbusiness@gmail.com
License: MIT
Project-URL: Source, https://github.com/muhammad-fiaz/dotsetup
Project-URL: Bug Reports, https://github.com/muhammad-fiaz/dotsetup/issues
Project-URL: Buy me a Coffee!, https://buymeacoffee.com/muhammadfiaz
Project-URL: Patreon, https://patreon.com/muhammadfiaz
Project-URL: Ko-fi, https://ko-fi.com/muhammadfiaz
Project-URL: GitHub Sponsors, https://github.com/sponsors/muhammad-fiaz
Project-URL: Open Collective, https://opencollective.com/muhammadfiaz
Keywords: configuration management environment variables setup tool
Classifier: Development Status :: 3 - Alpha
Classifier: Intended Audience :: Developers
Classifier: License :: OSI Approved :: MIT License
Classifier: Programming Language :: Python
Classifier: Programming Language :: Python :: 3
Classifier: Programming Language :: Python :: 3.6
Classifier: Programming Language :: Python :: 3.7
Classifier: Programming Language :: Python :: 3.8
Classifier: Programming Language :: Python :: 3.9
Classifier: Topic :: Software Development :: Libraries :: Python Modules
License-File: LICENSE
